MANIFEST.in
README.md
setup.cfg
setup.py
gfa/__init__.py
gfa/load_param.py
gfa/log_config.py
gfa.egg-info/PKG-INFO
gfa.egg-info/SOURCES.txt
gfa.egg-info/dependency_links.txt
gfa.egg-info/entry_points.txt
gfa.egg-info/not-zip-safe
gfa.egg-info/requires.txt
gfa.egg-info/top_level.txt
gfa/field_analysis/FallaOkada.py
gfa/field_analysis/__init__.py
gfa/field_analysis/field.py
gfa/field_analysis/fun_fig.py
gfa/field_analysis/geometry.py
gfa/gnss_analysis/ModelControl.py
gfa/gnss_analysis/ModeloTrayectoria.py
gfa/gnss_analysis/TimeSeriesControl.py
gfa/gnss_analysis/__init__.py
gfa/gnss_analysis/fun_datos.py
gfa/gnss_analysis/fun_tools.py
gfa/gnss_analysis/fun_tsplot.py
gfa/gnss_analysis/fun_vector.py
gfa/gnss_analysis/hvsd.py
gfa/gnss_analysis/loadGPS.py
gfa/gnss_analysis/model_accions.py
gfa/scripts/__init__.py
gfa/scripts/example_principalstrain.py
gfa/scripts/gfa.py
gfa/scripts/gfa_configure.py
gfa/scripts/lineal_model.py
gfa/scripts/ts_build.py
gfa/scripts/ts_buildmodelall.py
gfa/scripts/ts_plot.py
gfa/scripts/ts_select.py
gfa/scripts/ts_vector.py
gfa/scripts/ui_buildmodel.py
gfa/scripts/vorticity.py
gfa/test/__init__.py
gfa/test/interpol_test.py
gfa/test/test_import.py