Metadata-Version: 1.0
Name: gfa
Version: 1.3.3
Summary: Python tools for the geospatial analysis of a velocityfield, using Davis & Titus (2011) and Bevis & Brown (2014) papers.
Home-page: https://github.com/VicenteYanez/GFA
Author: Vicente Yanez
Author-email: vicenteyanez@protonmail.com
License: GLP-3
Keywords: gnss gps trajectory vorticity geospatial
Platform: UNKNOWN
